cryodata/__init__.py
cryodata/cryoemDataset.py
cryodata/dataset_resample.py
cryodata/cs_star_translate/__init__.py
cryodata/cs_star_translate/cs2star.py
cryodata/cs_star_translate/generate_cs_file.py
cryodata/cs_star_translate/utils.py
cryodata/cs_star_translate/pyem/__init__.py
cryodata/cs_star_translate/pyem/ctf.py
cryodata/cs_star_translate/pyem/mrc.py
cryodata/cs_star_translate/pyem/plot.py
cryodata/cs_star_translate/pyem/star.py
cryodata/cs_star_translate/pyem/algo/__init__.py
cryodata/cs_star_translate/pyem/algo/algo.py
cryodata/cs_star_translate/pyem/algo/algo_numba.py
cryodata/cs_star_translate/pyem/geom/__init__.py
cryodata/cs_star_translate/pyem/geom/convert.py
cryodata/cs_star_translate/pyem/geom/convert_numba.py
cryodata/cs_star_translate/pyem/geom/geom.py
cryodata/cs_star_translate/pyem/geom/geom_numba.py
cryodata/cs_star_translate/pyem/geom/quat.py
cryodata/cs_star_translate/pyem/geom/quat_numba.py
cryodata/cs_star_translate/pyem/metadata/__init__.py
cryodata/cs_star_translate/pyem/metadata/cistem.py
cryodata/cs_star_translate/pyem/metadata/cryosparc0.py
cryodata/cs_star_translate/pyem/metadata/cryosparc2.py
cryodata/cs_star_translate/pyem/util/__init__.py
cryodata/cs_star_translate/pyem/util/util.py
cryodata/cs_star_translate/pyem/vop/__init__.py
cryodata/cs_star_translate/pyem/vop/binary.py
cryodata/cs_star_translate/pyem/vop/vop.py
cryodata/cs_star_translate/pyem/vop/vop_numba.py
cryodata/data_preprocess/__init__.py
cryodata/data_preprocess/fft.py
cryodata/data_preprocess/lmdb_preprocess.py
cryodata/data_preprocess/mrc.py
cryodata/data_preprocess/mrc_preprocess.py
src/__init__.py
src/cryoemDataset.py
src/dataset_resample.py
src/evaluator.py
src/utils.py
src/cs_star_translate/__init__.py
src/cs_star_translate/cs2star.py
src/cs_star_translate/generate_cs_file.py
src/cs_star_translate/utils.py
src/cs_star_translate/pyem/__init__.py
src/cs_star_translate/pyem/ctf.py
src/cs_star_translate/pyem/mrc.py
src/cs_star_translate/pyem/plot.py
cryodata-0.1.1b5.dist-info/METADATA
cryodata-0.1.1b5.dist-info/WHEEL
cryodata-0.1.1b5.dist-info/top_level.txt
cryodata-0.1.1b5.dist-info/RECORD
